cacherator/__init__.py
cacherator/cached_function.py
cacherator/cacherator.py
cacherator/date_time_encoder.py
cacherator-1.0.11.dist-info/METADATA
cacherator-1.0.11.dist-info/WHEEL
cacherator-1.0.11.dist-info/top_level.txt
cacherator-1.0.11.dist-info/RECORD
