Metadata-Version: 2.4
Name: cacherator
Version: 1.0.11
Summary: A Python library for persistent JSON-based caching of class state and function results.
Author-email: Arved Klöhn <arved.kloehn@gmail.com>
License: MIT
Project-URL: Source, https://github.com/Redundando/cacherator
Keywords: cache,json,data storage
Classifier: Programming Language :: Python :: 3
Classifier: License :: OSI Approved :: MIT License
Classifier: Operating System :: OS Independent
Classifier: Development Status :: 4 - Beta
Classifier: Topic :: Software Development :: Libraries
Classifier: Topic :: Utilities
Requires-Python: >=3.7
Requires-Dist: python-slugify
Requires-Dist: logorator
